test_package/__init__.py
test_package/module1.py
julien_test_package_01-0.1.0.dist-info/METADATA
julien_test_package_01-0.1.0.dist-info/WHEEL
julien_test_package_01-0.1.0.dist-info/top_level.txt
julien_test_package_01-0.1.0.dist-info/RECORD
