Metadata-Version: 2.1
Name: julien-test-package-01
Version: 0.1.0
Summary: A description of your package
Home-page: https://github.com/yourusername/your-repo
Author: Your Name
Author-email: youremail@example.com
Classifier: Programming Language :: Python :: 3
